weco/__init__.py
weco/api.py
weco/auth.py
weco/cli.py
weco/constants.py
weco/credits.py
weco/optimizer.py
weco/panels.py
weco/utils.py
weco-0.3.7.dist-info/licenses/LICENSE
weco-0.3.7.dist-info/METADATA
weco-0.3.7.dist-info/WHEEL
weco-0.3.7.dist-info/entry_points.txt
weco-0.3.7.dist-info/top_level.txt
weco-0.3.7.dist-info/RECORD
