Metadata-Version: 2.4
Name: weco
Version: 0.3.7
Summary: Documentation for `weco`, a CLI for using Weco AI's code optimizer.
Author-email: Weco AI Team <contact@weco.ai>
License: 
Project-URL: Homepage, https://github.com/WecoAI/weco-cli
Keywords: AI,Code Optimization,Code Generation
Classifier: Programming Language :: Python :: 3
Classifier: Operating System :: OS Independent
Classifier: License :: OSI Approved :: Apache Software License
Requires-Python: >=3.8
License-File: LICENSE
Requires-Dist: requests
Requires-Dist: rich
Requires-Dist: packaging
Requires-Dist: gitingest
Requires-Dist: fastapi
Requires-Dist: slowapi
Requires-Dist: psutil
Provides-Extra: dev
Requires-Dist: ruff; extra == "dev"
Requires-Dist: build; extra == "dev"
Requires-Dist: setuptools_scm; extra == "dev"
Requires-Dist: pytest>=7.0.0; extra == "dev"
Dynamic: license-file
